indexed_gzip_fileobj_fork_epicfaace-1.5.4.dist-info/RECORD
indexed_gzip_fileobj_fork_epicfaace-1.5.4.dist-info/LICENSE
indexed_gzip_fileobj_fork_epicfaace-1.5.4.dist-info/WHEEL
indexed_gzip_fileobj_fork_epicfaace-1.5.4.dist-info/top_level.txt
indexed_gzip_fileobj_fork_epicfaace-1.5.4.dist-info/METADATA
indexed_gzip_fileobj_fork_epicfaace.libs/libz-9f7255d3.so.1.2.3
indexed_gzip_fileobj_fork_epicfaace/indexed_gzip_fileobj_fork_epicfaace.cpython-35m-i386-linux-gnu.so
indexed_gzip_fileobj_fork_epicfaace/__init__.py
indexed_gzip_fileobj_fork_epicfaace/tests/ctest_zran.cpython-35m-i386-linux-gnu.so
indexed_gzip_fileobj_fork_epicfaace/tests/conftest.py
indexed_gzip_fileobj_fork_epicfaace/tests/__init__.py
indexed_gzip_fileobj_fork_epicfaace/tests/test_indexed_gzip_fileobj_fork_epicfaace.py
indexed_gzip_fileobj_fork_epicfaace/tests/benchmark.py
indexed_gzip_fileobj_fork_epicfaace/tests/__main__.py
indexed_gzip_fileobj_fork_epicfaace/tests/test_indexed_gzip_fileobj_fork_epicfaace_threading.py
indexed_gzip_fileobj_fork_epicfaace/tests/test_zran.py
indexed_gzip_fileobj_fork_epicfaace/tests/test_nibabel_integration.py
indexed_gzip_fileobj_fork_epicfaace/tests/ctest_indexed_gzip_fileobj_fork_epicfaace.cpython-35m-i386-linux-gnu.so
