Metadata-Version: 2.1
Name: indexed-gzip-fileobj-fork-epicfaace
Version: 1.5.4
Summary: Fast random access of gzip files in Python
Home-page: https://github.com/pauldmccarthy/indexed_gzip_fileobj_fork_epicfaace
Author: Paul McCarthy
Author-email: pauldmccarthy@gmail.com
License: zlib
Platform: UNKNOWN
Classifier: Development Status :: 3 - Alpha
Classifier: Intended Audience :: Developers
Classifier: License :: OSI Approved :: zlib/libpng License
Classifier: Programming Language :: C
Classifier: Programming Language :: Cython
Classifier: Programming Language :: Python :: 2
Classifier: Programming Language :: Python :: 3
Classifier: Topic :: System :: Archiving :: Compression
